mex/__init__.py
mex/py.typed
mex/model/__init__.py
mex/model/entities/concept-scheme.json
mex/model/entities/concept.json
mex/model/entities/extracted-access-platform.json
mex/model/entities/extracted-activity.json
mex/model/entities/extracted-bibliographic-resource.json
mex/model/entities/extracted-consent.json
mex/model/entities/extracted-contact-point.json
mex/model/entities/extracted-distribution.json
mex/model/entities/extracted-organization.json
mex/model/entities/extracted-organizational-unit.json
mex/model/entities/extracted-person.json
mex/model/entities/extracted-primary-source.json
mex/model/entities/extracted-resource.json
mex/model/entities/extracted-variable-group.json
mex/model/entities/extracted-variable.json
mex/model/entities/merged-access-platform.json
mex/model/entities/merged-activity.json
mex/model/entities/merged-bibliographic-resource.json
mex/model/entities/merged-consent.json
mex/model/entities/merged-contact-point.json
mex/model/entities/merged-distribution.json
mex/model/entities/merged-organization.json
mex/model/entities/merged-organizational-unit.json
mex/model/entities/merged-person.json
mex/model/entities/merged-primary-source.json
mex/model/entities/merged-resource.json
mex/model/entities/merged-variable-group.json
mex/model/entities/merged-variable.json
mex/model/extension/definition.json
mex/model/fields/identifier.json
mex/model/fields/link.json
mex/model/fields/text.json
mex/model/i18n/de.po
mex/model/i18n/en.po
mex/model/vocabularies/access-restriction.json
mex/model/vocabularies/activity-type.json
mex/model/vocabularies/anonymization-pseudonymization.json
mex/model/vocabularies/api-type.json
mex/model/vocabularies/bibliographic-resource-type.json
mex/model/vocabularies/concept-schemes.json
mex/model/vocabularies/consent-status.json
mex/model/vocabularies/consent-type.json
mex/model/vocabularies/data-processing-state.json
mex/model/vocabularies/frequency.json
mex/model/vocabularies/language.json
mex_model-4.8.0.dist-info/METADATA
mex_model-4.8.0.dist-info/WHEEL
mex_model-4.8.0.dist-info/licenses/AUTHORS
mex_model-4.8.0.dist-info/licenses/LICENSE
mex_model-4.8.0.dist-info/RECORD
