Metadata-Version: 2.4
Name: mex-model
Version: 4.8.0
Summary: JSON schema files defining the MEx metadata model.
Project-URL: Repository, https://github.com/robert-koch-institut/mex-model
Author-email: MEx Team <mex@rki.de>
License: MIT License
License-File: AUTHORS
License-File: LICENSE
Requires-Python: <3.12,>=3.11
Requires-Dist: importlib-resources>=1.3; python_version < '3.10'
Provides-Extra: dev
Requires-Dist: ipdb>=0.13; extra == 'dev'
Requires-Dist: mypy>=1; extra == 'dev'
Requires-Dist: pytest-cov>=6; extra == 'dev'
Requires-Dist: pytest-random-order>=1; extra == 'dev'
Requires-Dist: pytest-xdist>=3; extra == 'dev'
Requires-Dist: pytest>=8; extra == 'dev'
Requires-Dist: ruff>=0.14; extra == 'dev'
Requires-Dist: sphinx-jsonschema; extra == 'dev'
Requires-Dist: sphinx<9; extra == 'dev'
